abc_algorithm/__init__.py
abc_algorithm/main.py
abc_algorithm-0.0.2.dist-info/WHEEL
abc_algorithm-0.0.2.dist-info/METADATA
abc_algorithm-0.0.2.dist-info/RECORD
