Metadata-Version: 2.1
Name: abc_algorithm
Version: 0.0.2
Summary: Artificial Bee Colony Algorithm for educational purposes
Home-page: UNKNOWN
License: UNKNOWN
Author: Gabriel Kabbe
Author-email: gabriel.kabbe@chemie.uni-halle.de
Classifier: License :: OSI Approved :: GNU General Public License v3 or later (GPLv3+)
Requires-Dist: pytest >= 5.0.1; extra == "test"
Provides-Extra: test
